comprehensive_solana_diagnostic/__init__.py
comprehensive_solana_diagnostic/comprehensive_solana_diagnostic.py
comprehensive_solana_diagnostic-0.1.5.dist-info/licenses/LICENSE
comprehensive_solana_diagnostic-0.1.5.dist-info/METADATA
comprehensive_solana_diagnostic-0.1.5.dist-info/WHEEL
comprehensive_solana_diagnostic-0.1.5.dist-info/top_level.txt
comprehensive_solana_diagnostic-0.1.5.dist-info/RECORD
