Metadata-Version: 2.4
Name: comprehensive-solana-diagnostic
Version: 0.1.5
Summary: A Python tool for comprehensive diagnostics of Solana nodes and networks.
Author-email: homezloco <homezloco@hotmail.com>
License: MIT License
Project-URL: Homepage, https://github.com/homezloco/comprehensive-solana-diagnostic
Project-URL: Issues, https://github.com/homezloco/comprehensive-solana-diagnostic/issues
Classifier: Programming Language :: Python :: 3
Classifier: Operating System :: OS Independent
Requires-Python: >=3.8
License-File: LICENSE
Requires-Dist: aiohttp>=3.8.0
Requires-Dist: pydantic>=2.0.0
Requires-Dist: click>=8.0.0
Dynamic: license-file
Dynamic: requires-python
